setup.py
django_heroku_sendgridify.egg-info/PKG-INFO
django_heroku_sendgridify.egg-info/SOURCES.txt
django_heroku_sendgridify.egg-info/dependency_links.txt
django_heroku_sendgridify.egg-info/top_level.txt
sendgridify/__init__.py