Metadata-Version: 1.0
Name: django-heroku-sendgridify
Version: 0.1.1
Summary: Automatic email configuration for the Django/Heroku/SendGrid stack
Home-page: https://github.com/chuckharmston/django-heroku-sendgridify
Author: Chuck Harmston
Author-email: chuck@chuckharmston.com
License: MIT
Keywords: django heroku cloud email sendgrid sendgridify
Platform: UNKNOWN
Classifier: Development Status :: 4 - Beta
Classifier: Environment :: Web Environment
Classifier: Framework :: Django
Classifier: Intended Audience :: Developers
Classifier: Intended Audience :: End Users/Desktop
Classifier: License :: OSI Approved :: MIT License
Classifier: Natural Language :: English
Classifier: Operating System :: OS Independent
Classifier: Programming Language :: Python
Classifier: Topic :: Communications
